_klimits.cpython-311-x86_64-linux-gnu.so
klimits/test_trajectory_generation.py
klimits/__init__.py
klimits/trajectory_plotter.py
klimits.libs/libgomp-a34b3233.so.1.0.0
klimits-1.1.3.dist-info/METADATA
klimits-1.1.3.dist-info/RECORD
klimits-1.1.3.dist-info/top_level.txt
klimits-1.1.3.dist-info/WHEEL
klimits-1.1.3.dist-info/LICENSE
