Metadata-Version: 2.1
Name: klimits
Version: 1.1.3
Summary: An action space representation for learning robot trajectories without exceeding limits on the position, velocity, acceleration and jerk of each robot joint.
Home-page: https://github.com/translearn/limits
Author: Jonas C. Kiemel
Author-email: jonas.kiemel@kit.edu
License: MIT
Classifier: License :: OSI Approved :: MIT License
Classifier: Intended Audience :: Developers
License-File: LICENSE
Requires-Dist: numpy
Requires-Dist: matplotlib
